atbu/tools/__init__.py
atbu/tools/backup/__init__.py
atbu/tools/backup/backup_cmdline.py
atbu/tools/backup/backup_constants.py
atbu/tools/backup/backup_core.py
atbu/tools/backup/backup_dao.py
atbu/tools/backup/backup_entities.py
atbu/tools/backup/backup_selections.py
atbu/tools/backup/chunk_reader.py
atbu/tools/backup/command_line.py
atbu/tools/backup/config.py
atbu/tools/backup/config_migration_helpers.py
atbu/tools/backup/constants.py
atbu/tools/backup/credentials.py
atbu/tools/backup/creds_cmdline.py
atbu/tools/backup/db_api.py
atbu/tools/backup/exception.py
atbu/tools/backup/global_hasher.py
atbu/tools/backup/list_items.py
atbu/tools/backup/recover.py
atbu/tools/backup/restore.py
atbu/tools/backup/storage_def_credentials.py
atbu/tools/backup/verify.py
atbu/tools/backup/yubikey_helpers.py
atbu/tools/backup/storage_interface/__init__.py
atbu/tools/backup/storage_interface/azure.py
atbu/tools/backup/storage_interface/base.py
atbu/tools/backup/storage_interface/filesystem.py
atbu/tools/backup/storage_interface/google.py
atbu/tools/backup/storage_interface/libcloud.py
atbu/tools/persisted_info/__init__.py
atbu/tools/persisted_info/arrange.py
atbu/tools/persisted_info/database.py
atbu/tools/persisted_info/diff.py
atbu/tools/persisted_info/file_info.py
atbu/tools/persisted_info/update_digests.py
atbu_pkg-0.0.47.dist-info/LICENSE
atbu_pkg-0.0.47.dist-info/METADATA
atbu_pkg-0.0.47.dist-info/WHEEL
atbu_pkg-0.0.47.dist-info/entry_points.txt
atbu_pkg-0.0.47.dist-info/top_level.txt
atbu_pkg-0.0.47.dist-info/RECORD
